creditriskutilities/__init__.py
creditriskutilities/package_utils.py
creditriskutilities-1.0.2.dist-info/licenses/LICENSE
creditriskutilities-1.0.2.dist-info/METADATA
creditriskutilities-1.0.2.dist-info/WHEEL
creditriskutilities-1.0.2.dist-info/top_level.txt
creditriskutilities-1.0.2.dist-info/RECORD
