Metadata-Version: 2.4
Name: creditriskutilities
Version: 1.0.2
Summary: Reusable credit risk model evaluation and data utility functions.
Author-email: Stallon Pinto <stallonpinto03@gmail.com>, Ayush Mehul Joshi <ayushmehuljoshi@gmail.com>, Zhanerke Zhumash <szhanerz@gmail.com>
License: MIT
Project-URL: Homepage, https://github.com/DSCI-310-2025/creditriskutilities
Project-URL: Repository, https://github.com/DSCI-310-2025/creditriskutilities
Project-URL: Documentation, https://dsci-310-2025.github.io/creditriskutilities
Requires-Python: >=3.8
License-File: LICENSE
Requires-Dist: pandas
Requires-Dist: numpy
Requires-Dist: scikit-learn
Requires-Dist: matplotlib
Requires-Dist: seaborn
Provides-Extra: dev
Requires-Dist: pytest; extra == "dev"
Requires-Dist: pytest-cov; extra == "dev"
Dynamic: license-file
